dnntools/__init__.py
dnntools/caffe_converter/__init__.py
dnntools/caffe_converter/caffe2daq.py
dnntools/model_writer/__init__.py
dnntools/model_writer/model_writer.py
dnntools-0.1.8.dist-info/METADATA
dnntools-0.1.8.dist-info/RECORD
dnntools-0.1.8.dist-info/WHEEL
dnntools-0.1.8.dist-info/top_level.txt
