Metadata-Version: 2.1
Name: dnntools
Version: 0.1.8
Summary: Convert caffemodel to DNNLibrary's .daq file
Home-page: https://github.com/daquexian/dnnconverttool
Author: daquexian
Author-email: daquexian566@gmail.com
License: Apache
Keywords: deep-learning NNAPI DNNLibrary Android
Platform: UNKNOWN
Classifier: Development Status :: 4 - Beta
Classifier: Intended Audience :: Developers
Classifier: License :: OSI Approved :: Apache Software License
Classifier: Programming Language :: Python :: 3 :: Only
Classifier: Programming Language :: Python :: 3.5
Classifier: Programming Language :: Python :: 3.6
Classifier: Programming Language :: Python :: 3.7
Classifier: Topic :: Scientific/Engineering
Classifier: Topic :: Software Development
Requires-Python: >=3.5
Requires-Dist: numpy
Requires-Dist: protobuf
